{
  "title": "Creep",
  "artist": "Radiohead",
  "songChords": "[Intro]\nG  B  C  Cm\nG  B  C  Cm\n\n[Verse 1]\nG                    B\nWhen you were here before\nC                    Cm\nCouldn't look you in the eye\nG                    B\nYou're just like an angel\nC                    Cm\nYour skin makes me cry\nG                    B\nYou float like a feather\nC                    Cm\nIn a beautiful world\nG                    B\nI wish I was special\nC              Cm\nYou're so fuckin' special\n\n[Chorus]\nG              B\nBut I'm a creep\nC              Cm\nI'm a weirdo\nG                    B\nWhat the hell am I doing here?\nC              Cm\nI don't belong here\n\n[Verse 2]\nG                    B\nI don't care if it hurts\nC                    Cm\nI want to have control\nG                    B\nI want a perfect body\nC                    Cm\nI want a perfect soul\nG                    B\nI want you to notice\nC                    Cm\nWhen I'm not around\nG                    B\nYou're so fuckin' special\nC              Cm\nI wish I was special\n\n[Chorus]\nG              B\nBut I'm a creep\nC              Cm\nI'm a weirdo\nG                    B\nWhat the hell am I doing here?\nC              Cm\nI don't belong here\n\n[Bridge]\nG          B\nShe's running out again\nC          Cm\nShe's running out\nG          B          C     Cm\nShe run, run, run, run\nG  B  C  Cm\n\n[Final Chorus]\nG                    B\nWhatever makes you happy\nC                    Cm\nWhatever you want\nG                    B\nYou're so fuckin' special\nC              Cm\nI wish I was special\n\nG              B\nBut I'm a creep\nC              Cm\nI'm a weirdo\nG                    B\nWhat the hell am I doing here?\nC              Cm\nI don't belong here\nC              Cm\nI don't belong here",
  "songKey": "G",
  "guitarTuning": [
    "E",
    "A",
    "D",
    "G",
    "B",
    "E"
  ],
  "guitarCapo": 0
}